[
  {
    "inputs": [
      {
        "internalType": "address",
        "name": "_petNFT",
        "type": "address"
      },
      {
        "internalType": "address",
        "name": "_petCoin",
        "type": "address"
      }
    ],
    "stateMutability": "nonpayable",
    "type": "constructor"
  },
  {
    "anonymous": false,
    "inputs": [
      {
        "indexed": true,
        "internalType": "address",
        "name": "owner",
        "type": "address"
      },
      {
        "indexed": false,
        "internalType": "uint256",
        "name": "parent1Id",
        "type": "uint256"
      },
      {
        "indexed": false,
        "internalType": "uint256",
        "name": "parent2Id",
        "type": "uint256"
      },
      {
        "indexed": false,
        "internalType": "uint256",
        "name": "childId",
        "type": "uint256"
      }
    ],
    "name": "PetsBreed",
    "type": "event"
  },
  {
    "inputs": [
      {
        "internalType": "uint256",
        "name": "parent1Id",
        "type": "uint256"
      },
      {
        "internalType": "uint256",
        "name": "parent2Id",
        "type": "uint256"
      },
      {
        "internalType": "string",
        "name": "name",
        "type": "string"
      }
    ],
    "name": "breedPets",
    "outputs": [
      {
        "internalType": "uint256",
        "name": "",
        "type": "uint256"
      }
    ],
    "stateMutability": "nonpayable",
    "type": "function"
  },
  {
    "inputs": [],
    "name": "breedingFee",
    "outputs": [
      {
        "internalType": "uint256",
        "name": "",
        "type": "uint256"
      }
    ],
    "stateMutability": "view",
    "type": "function"
  },
  {
    "inputs": [
      {
        "internalType": "uint256",
        "name": "petId",
        "type": "uint256"
      }
    ],
    "name": "canBreed",
    "outputs": [
      {
        "internalType": "bool",
        "name": "",
        "type": "bool"
      }
    ],
    "stateMutability": "view",
    "type": "function"
  },
  {
    "inputs": [],
    "name": "cooldownTime",
    "outputs": [
      {
        "internalType": "uint256",
        "name": "",
        "type": "uint256"
      }
    ],
    "stateMutability": "view",
    "type": "function"
  },
  {
    "inputs": [
      {
        "internalType": "uint256",
        "name": "petId",
        "type": "uint256"
      }
    ],
    "name": "getCooldownTimeLeft",
    "outputs": [
      {
        "internalType": "uint256",
        "name": "",
        "type": "uint256"
      }
    ],
    "stateMutability": "view",
    "type": "function"
  },
  {
    "inputs": [
      {
        "internalType": "uint256",
        "name": "",
        "type": "uint256"
      }
    ],
    "name": "lastBreedingTime",
    "outputs": [
      {
        "internalType": "uint256",
        "name": "",
        "type": "uint256"
      }
    ],
    "stateMutability": "view",
    "type": "function"
  },
  {
    "inputs": [],
    "name": "petCoin",
    "outputs": [
      {
        "internalType": "contract PetCoin",
        "name": "",
        "type": "address"
      }
    ],
    "stateMutability": "view",
    "type": "function"
  },
  {
    "inputs": [],
    "name": "petNFT",
    "outputs": [
      {
        "internalType": "contract PetNFT",
        "name": "",
        "type": "address"
      }
    ],
    "stateMutability": "view",
    "type": "function"
  },
  {
    "inputs": [
      {
        "internalType": "uint256",
        "name": "_fee",
        "type": "uint256"
      }
    ],
    "name": "setBreedingFee",
    "outputs": [],
    "stateMutability": "nonpayable",
    "type": "function"
  },
  {
    "inputs": [
      {
        "internalType": "uint256",
        "name": "_time",
        "type": "uint256"
      }
    ],
    "name": "setCooldownTime",
    "outputs": [],
    "stateMutability": "nonpayable",
    "type": "function"
  }
]